tell_whois_who/__init__.py
tell_whois_who/cli.py
tell_whois_who-0.2.0.dist-info/LICENSE
tell_whois_who-0.2.0.dist-info/METADATA
tell_whois_who-0.2.0.dist-info/WHEEL
tell_whois_who-0.2.0.dist-info/entry_points.txt
tell_whois_who-0.2.0.dist-info/top_level.txt
tell_whois_who-0.2.0.dist-info/RECORD
